README.md
setup.cfg
setup.py
thresher/__init__.py
thresher/algorithm.py
thresher/exceptions.py
thresher/interface.py
thresher/oracle.py
thresher/utils.py
thresher/algs/__init__.py
thresher/algs/common/__init__.py
thresher/algs/common/meta_optimizer.py
thresher/algs/common/stochastic.py
thresher/algs/common/tools.py
thresher/algs/genetic/__init__.py
thresher/algs/genetic/compute.py
thresher/algs/grid/__init__.py
thresher/algs/grid/compute.py
thresher/algs/linear/__init__.py
thresher/algs/linear/compute.py
thresher/algs/sgd/__init__.py
thresher/algs/sgd/compute.py
thresher_py.egg-info/PKG-INFO
thresher_py.egg-info/SOURCES.txt
thresher_py.egg-info/dependency_links.txt
thresher_py.egg-info/requires.txt
thresher_py.egg-info/top_level.txt