Metadata-Version: 2.1
Name: thresher-py
Version: 0.1.2
Summary: Find threshold for fine-tuning output from predict_proba
Home-page: https://github.com/oskar-j/thresher
Author: Oskar Jarczyk
Author-email: oskar.jarczyk@gmail.com
Maintainer: Oskar Jarczyk
Maintainer-email: oskar.jarczyk@gmail.com
License: MIT
Download-URL: https://github.com/oskar-j/thresher/archive/v_01_2.tar.gz
Platform: UNKNOWN
Classifier: Development Status :: 3 - Alpha
Classifier: Intended Audience :: Science/Research
Classifier: Topic :: Scientific/Engineering :: Artificial Intelligence
Classifier: License :: OSI Approved
Classifier: Programming Language :: Python :: 3
Classifier: Programming Language :: Python :: 3.5
Classifier: Programming Language :: Python :: 3.6
Classifier: Programming Language :: Python :: 3.7
